CHANGES.txt
README.txt
bootstrap.py
buildout.cfg
setup.py
docs/LICENSE.GPL
docs/LICENSE.txt
plone/__init__.py
plone.transforms.egg-info/PKG-INFO
plone.transforms.egg-info/SOURCES.txt
plone.transforms.egg-info/dependency_links.txt
plone.transforms.egg-info/entry_points.txt
plone.transforms.egg-info/namespace_packages.txt
plone.transforms.egg-info/not-zip-safe
plone.transforms.egg-info/requires.txt
plone.transforms.egg-info/top_level.txt
plone/transforms/TODO.txt
plone/transforms/__init__.py
plone/transforms/chain.py
plone/transforms/command.py
plone/transforms/configure.zcml
plone/transforms/engine.py
plone/transforms/identity.py
plone/transforms/log.py
plone/transforms/message.py
plone/transforms/meta.zcml
plone/transforms/metaconfigure.py
plone/transforms/metadirectives.py
plone/transforms/pipe.py
plone/transforms/stringiter.py
plone/transforms/transform.py
plone/transforms/utils.py
plone/transforms/binary/__init__.py
plone/transforms/binary/configure.zcml
plone/transforms/binary/doc_html_wv.py
plone/transforms/binary/doc_txt_wv.py
plone/transforms/binary/pdf_html.py
plone/transforms/binary/xls_html_xlhtml.py
plone/transforms/binary/tests/__init__.py
plone/transforms/binary/tests/base.py
plone/transforms/binary/tests/layer.py
plone/transforms/binary/tests/test_doc.py
plone/transforms/binary/tests/test_pdf_html.py
plone/transforms/binary/tests/input/test.doc
plone/transforms/binary/tests/input/test_doc.doc
plone/transforms/binary/tests/input/test_odp.odp
plone/transforms/binary/tests/input/test_ods.ods
plone/transforms/binary/tests/input/test_odt.odt
plone/transforms/binary/tests/input/test_pdf_html.pdf
plone/transforms/binary/tests/input/test_pdf_html_complex.pdf
plone/transforms/binary/tests/input/test_ppt.ppt
plone/transforms/binary/tests/input/test_sxc.sxc
plone/transforms/binary/tests/input/test_sxi.sxi
plone/transforms/binary/tests/input/test_sxw.sxw
plone/transforms/image/__init__.py
plone/transforms/image/bmp.py
plone/transforms/image/configure.zcml
plone/transforms/image/gif.py
plone/transforms/image/jpeg.py
plone/transforms/image/pcx.py
plone/transforms/image/pil.py
plone/transforms/image/png.py
plone/transforms/image/ppm.py
plone/transforms/image/tiff.py
plone/transforms/image/tests/__init__.py
plone/transforms/image/tests/base.py
plone/transforms/image/tests/layer.py
