Metadata-Version: 1.0
Name: plone.transforms
Version: 1.1a1
Summary: Transformation registry and utilities.
Home-page: http://pypi.python.org/pypi/plone.transforms
Author: Plone Foundation
Author-email: plone-developers@lists.sourceforge.net
License: GPL
Keywords: Plone Transformation
Platform: UNKNOWN
Classifier: Framework :: Plone
Classifier: Framework :: Zope2
Classifier: Programming Language :: Python
